example_package/__init__.py
example_package/example.py
example_package/example2.py
example_package/sayhello.py
gk_datasci_GEORGE_KULANGARA-0.0.1.dist-info/LICENSE
gk_datasci_GEORGE_KULANGARA-0.0.1.dist-info/METADATA
gk_datasci_GEORGE_KULANGARA-0.0.1.dist-info/WHEEL
gk_datasci_GEORGE_KULANGARA-0.0.1.dist-info/top_level.txt
gk_datasci_GEORGE_KULANGARA-0.0.1.dist-info/RECORD
