Metadata-Version: 2.1
Name: gk_datasci-GEORGE-KULANGARA
Version: 0.0.1
Summary: Set of tools to automate data analysis processes
Home-page: https://github.com/KulangaraG/GK_DataSci
Author: GEORGE KULANGARA
Author-email: georgekulangara98@gmail.com
Project-URL: Bug Tracker, https://github.com/KulangaraG/GK_DataSci/issues
Classifier: Programming Language :: Python :: 3
Classifier: License :: OSI Approved :: MIT License
Classifier: Operating System :: OS Independent
Requires-Python: >=3.6
License-File: LICENSE
